[
  {
    "id": "burger-black",
    "category": "FAST-FOOD",
    "name": "Бургер \"Черный\" (комбо)",
    "price": 3900,
    "description": "Сочный говяжий бургер с черной булочкой, картофель фри и напиток",
    "image": "img/burger-black.jpg",
    "Столбец 7": null
  },
  {
    "id": "burger-devon",
    "category": "FAST-FOOD",
    "name": "Бургер \"Девонй\" (комбо)",
    "price": 4100,
    "description": "Двойной бургер с беконом, картофель фри и напиток",
    "image": "img/placeholder.jpg",
    "Столбец 7": null
  },
  {
    "id": "pizza-pepperoni",
    "category": "FAST-FOOD",
    "name": "Пицца \"Пепперони\"",
    "price": 3500,
    "description": "Классическая пицца с пепперони и моцареллой",
    "image": "img/piza_peperony.jpg",
    "Столбец 7": null
  },
  {
    "id": "pizza-margarita",
    "category": "FAST-FOOD",
    "name": "Пицца \"Маргарита\"",
    "price": 2800,
    "description": "Традиционная итальянская пицца с томатами и базиликом",
    "image": "img/placeholder.jpg",
    "Столбец 7": null
  },
  {
    "id": "salad-greek",
    "category": "САЛАТЫ",
    "name": "Салат \"Греческий\"",
    "price": 1400,
    "description": "Свежие овощи, фета, маслины, оливковое масло",
    "image": "img/grecheskiy_salad.jpg",
    "Столбец 7": null
  },
  {
    "id": "ramen-chicken",
    "category": "СУПЫ",
    "name": "Рамен с курицей",
    "price": 2100,
    "description": "Японский суп с лапшой, курицей и яйцом",
    "image": "img/ramen-chicken.jpg.jpg",
    "Столбец 7": null
  },
  {
    "id": "belderim",
    "category": "БЛЮДА НА КОМПАНИЮ ПО ПРЕДЗАКАЗУ",
    "name": "Бельдерим из конины (большая тарелка на 5-6 чел)",
    "price": 18000,
    "description": "Традиционное казахское блюдо из конины. Требуется предзаказ за 2 часа",
    "image": "img/beshparmak.jpg",
    "Столбец 7": null
  },
  {
    "id": "schnitzel-beef",
    "category": "ГОРЯЧИЕ БЛЮДА",
    "name": "Шницель говяжий с сыром и овощами",
    "price": 2500,
    "description": "Сочный говяжий шницель с сыром и гарниром из овощей",
    "image": "img/placeholder.jpg",
    "Столбец 7": null
  },
  {
    "id": "schnitzel-turkey",
    "category": "ГОРЯЧИЕ БЛЮДА",
    "name": "Шницель из индюшки с картофелем фри",
    "price": 2500,
    "description": "Нежный шницель из индейки с картофелем фри",
    "image": "img/placeholder.jpg",
    "Столбец 7": null
  },
  {
    "id": "teriyaki",
    "category": "ГОРЯЧИЕ БЛЮДА",
    "name": "Курица терияки с рисом",
    "price": 3000,
    "description": "Куриное филе в соусе терияки с рисом и овощами",
    "image": "img/placeholder.jpg",
    "Столбец 7": null
  },
  {
    "id": "hauari-alakol",
    "category": "ГОРЯЧИЕ БЛЮДА",
    "name": "Хауари по-алакольски",
    "price": 2500,
    "description": "Местное блюдо из рыбы по фирменному рецепту",
    "image": "img/placeholder.jpg",
    "Столбец 7": null
  },
  {
    "id": "hauari-mergen",
    "category": "ГОРЯЧИЕ БЛЮДА",
    "name": "Хауари по-мергенски",
    "price": 2000,
    "description": "Традиционное рыбное блюдо с овощами",
    "image": "img/placeholder.jpg",
    "Столбец 7": null
  },
  {
    "id": "bread-cheese",
    "category": "ГОРЯЧИЕ БЛЮДА",
    "name": "Хлебный с сыром",
    "price": 1000,
    "description": "Запеченный хлеб с сырной начинкой",
    "image": "img/placeholder.jpg",
    "Столбец 7": null
  }
]